eecmip5/__init__.py
eecmip5/eecmip5.py
eecmip5-0.0.1.dist-info/DESCRIPTION.rst
eecmip5-0.0.1.dist-info/METADATA
eecmip5-0.0.1.dist-info/RECORD
eecmip5-0.0.1.dist-info/WHEEL
eecmip5-0.0.1.dist-info/metadata.json
eecmip5-0.0.1.dist-info/top_level.txt
