Metadata-Version: 2.0
Name: eecmip5
Version: 0.0.1
Summary: Download and manipulate CMIP5 climate simulations from Earth Engine
Home-page: https://github.com/csaybar/eecmip5
Author: Cesar Aybar
Author-email: csaybar@gmail.com
License: GNU General Public License v3
Keywords: eecmip5
Platform: UNKNOWN
Classifier: Development Status :: 2 - Pre-Alpha
Classifier: Intended Audience :: Developers
Classifier: License :: OSI Approved :: GNU General Public License v3 (GPLv3)
Classifier: Natural Language :: English
Classifier: Programming Language :: Python :: 2
Classifier: Programming Language :: Python :: 2.7
Classifier: Programming Language :: Python :: 3
Classifier: Programming Language :: Python :: 3.4
Classifier: Programming Language :: Python :: 3.5
Classifier: Programming Language :: Python :: 3.6
Classifier: Programming Language :: Python :: 3.7
